zmk_buddy/__init__.py
zmk_buddy/__main__.py
zmk_buddy/data/__init__.py
zmk_buddy/data/keymaps/__init__.py
zmk_buddy/data/keymaps/miryoku.yaml
zmk_buddy/learning.py
zmk_buddy/live.py
zmk_buddy/live_preflight.py
zmk_buddy/util.py
zmk_buddy/zmk_client.py
zmk_buddy-0.1.1.dist-info/METADATA
zmk_buddy-0.1.1.dist-info/WHEEL
zmk_buddy-0.1.1.dist-info/entry_points.txt
zmk_buddy-0.1.1.dist-info/licenses/LICENSE
zmk_buddy-0.1.1.dist-info/RECORD
