Metadata-Version: 2.4
Name: zmk-buddy
Version: 0.1.1
Summary: A live keymap visualization tool for ZMK keyboards.
License-Expression: GPL-3.0-or-later
License-File: LICENSE
Author: Kevin Hester
Author-email: kevinh@geeksville.com
Requires-Python: >=3.12,<3.15
Classifier: Programming Language :: Python :: 3
Classifier: Programming Language :: Python :: 3.12
Classifier: Programming Language :: Python :: 3.13
Classifier: Programming Language :: Python :: 3.14
Provides-Extra: dev
Requires-Dist: black ; extra == "dev"
Requires-Dist: bleak (>=0.22.0)
Requires-Dist: evdev (>=1.7) ; sys_platform == "linux"
Requires-Dist: keymap-drawer (>=0.22.1)
Requires-Dist: mypy ; extra == "dev"
Requires-Dist: platformdirs (>=4.0)
Requires-Dist: pylint ; extra == "dev"
Requires-Dist: pynput (>=1.7)
Requires-Dist: pyside6 (>=6.10.1)
Requires-Dist: pyyaml (>=6.0,<7.0)
Requires-Dist: types-pyyaml ; extra == "dev"
Project-URL: Homepage, https://github.com/geeksville/zmk-buddy
Project-URL: Repository, https://github.com/geeksville/zmk-buddy
Project-URL: issues, https://github.com/geeksville/zmk-buddy/issues
